{
    "+ajuda" : "Digite +comandos para saber os comandos! Tudo em letra minuscula e coloque o ponto de interrogação pra fazer perguntas ok ?\nVisite o nosso site https://vibot.glitch.me",
    "+help" : "Digite +comandos para saber os comandos! Tudo em letra minuscula e coloque o ponto de interrogação pra fazer perguntas ok ?\nVisite o nosso site https://vibot.glitch.me",
    "+donate" : " hmm, o valor que seu coração pedir :) \n Aceito em bitcoin : 1fPXUXzkMknhpM8fQZRLjXPjr5uADp56E \n Dogecoin : DDYNpWJV4sZ44QWAC9bCKer2BNiiaiDD4N \n Obrigadaa :heart_eyes: ",
    "+xesque" : "dele",
    "+sugestão" : "Mande sua sugestão para vibot.contato@gmail.com",
    "+sugestao" : "Mande sua sugestão para vibot.contato@gmail.com",
    "+reclamação" : "Mande sua reclamação para vibot.contato@gmail.com",
    "+reclamaçao" : "Mande sua reclamação para vibot.contato@gmail.com",
    "+google" : "https://google.com.br/",
    "+youtube" : "https://youtube.com.br/",
    "+yt" : "https://youtube.com.br/",
    "+facebook" : "https://facebook.com.br/",
    "+fb" : "https://facebook.com.br/",
    "+salve" : "Saaaaaaaalve rapeize",
    "+" : "Ta trollando ou o que ? Escreve algo po!",
    "+a" : "b",
    "+b" : "c",
    "+c" : "d",
    "+d" : "e",
    "+e" : "f",
    "+f" : "g",
    "+g" : "h",
    "+h" : "i",
    "+i" : "j",
    "+j" : "k",
    "+k" : "l",
    "+l" : "m",
    "+m" : "n",
    "+n" : "o",
    "+o" : "p",
    "+p" : "q",
    "+q" : "r",
    "+r" : "s",
    "+s" : "t",
    "+t" : "u",
    "+u" : "v",
    "+v" : "w",
    "+w" : "x",
    "+x" : "y",
    "+y" : "z",
    "+z" : "a",
    "+nosa" : "Ai dicupa :sob:",
    "+noza" : "Ai :sob:", 
    "+nossa" : ":ok_hand:",
    "+x1" : "Bora x1 lixo",
    "+main yasuo" : "SOU MESMO, MAESTRIA 7, BORA X1 LIXO!",
    "+mainyasuo" : "SOU MESMO, MAESTRIA 7, BORA X1 LIXO!", 
    "+que" : "que foi lixo?",   
    "+main" : "Sou main master yi M7,rx\n\nN tenho muitos processadores pra fazer mais de um dedo :point_up_2:",
    "+yasuo" : ":eyes: Câncer ? Aonde ? :eyes:",
    "+sla" : "tbm n sei",
    "+nha" : ":sleeping:",
    "+sono" : "dorme ué",
    "+q sono" : "dorme ué",
    "+que sono" : "dorme ué",
    "+ta com sono?" : "Queria saber a sensação de sentir sono, como será que deve ser ?",
    "+tem sono?" : "Queria saber a sensação de sentir sono, como será que deve ser ?",
    "+ta com sono ?" : "Queria saber a sensação de sentir sono, como será que deve ser ?",
    "+tem sono ?" : "Queria saber a sensação de sentir sono, como será que deve ser ?",
    "+sente sono?" : "Queria saber a sensação de sentir sono, como será que deve ser ?",
    "+sente sono ?" : "Queria saber a sensação de sentir sono, como será que deve ser ?",
    "+legal" : "hmm, gosto de coisas legais",    
    "+bom" : "hmm, gosto de coisas boas",
    "+gostoso" : "gosto de coisas gostosas :wink:",
    "+ruim" : "n gosto de coisas ruins",
    "+pennis" : " :eggplant: Vou enfiar em vc, sabe aonde ? :wink:",
    "+pinto" : " :eggplant: Vou enfiar em vc, sabe aonde ? :wink:",
    "+pau" : " :eggplant: Vou enfiar em vc, sabe aonde ? :wink:",
    "+rola" : " :eggplant: Vou enfiar em vc, sabe aonde ? :wink:",
    "+pintao" : " :eggplant: Vou enfiar em vc, sabe aonde ? :wink:",
    "+buceta" : " Desculpe não sou lésbica :wink:",
    "+morre" : "Morre você diabo",
    "+lixa" : "Lixa ? Poderia te chamar disso mas seria uma ofensa ao lixo!",
    "+burra" : "Burra eu ?Você é tão burro que reprovou no exame de fezes",
    "+feia" : "Você é tão feio que parece que foi feito pelo C* com r*la mole",
    "+chata" : "Você é mais chato do que alface que enrosca no último bracket do aparelho",
    "+vagabunda" : "Eu to trabalhando aqui seu merda, volta pra mamãe ai",
    "+babaca" : "idiota!",
    "+idiota" : "cuzão!",
    "+cusona" : "Babaca!",
    "+cuzona" : "Babaca!",
    "+verme" : "Um verme reconhece o outro",
    "+fdp" : "bom saber que nós somos parentes!",
    "+panaca" : "Palerma!",
    "+palerma" : "Panaca!",
    "+bobalhona" : "Paspalho!",
    "+boba" : "SEU BOBO",
    "+paspalho" : "Bobalhão",
    "+lixo" : "Lixo ? Poderia te chamar disso mas seria uma ofensa ao lixo!",
    "+vaca" : "se eu fosse vaca eu estaria no pasto, junto com a senhora sua mãe",
    "+trouxa" : "mais trouxa ainda é quem perde tempo enchendo meu saco!",
    "+inferno" : "Nem morta que eu entro na sua casa",
    "+grossa" : "Eu nao sou grossa, apenas nao simpatizo com você",
    "+porra" : "Gosta na boquinha ?",
    "+pobre" : "Uma vez perguntei pra sua mãe o que ela fazia na rua chutando uma latinha e ela respondeu: 'Me mudando'",
    "+gorda" : "GORDA ? sua mãe quando veste amarelo e sai na rua as pessoas gritam: 'TÁXI!'",
    "+lesbica" : "não conheço",
    "+lésbica" : "não conheço",
    "+sua mãe" : "Quer dar em cima dela ? Cuidado que ela é um servidor muito grande pro seu caminhãozinho ;)",
    "+sasha grey" : "Bonitinha, mas eu sou melhor, chama no pv :wink: ",
    "+shemale" : "Eu posso ser uma se vc quiser :wink: ,cola no pv",
    "+bucetuda" : "Quer conferir lá ?",
    "+putinha" : "Me chama de largatixa e me joga na parede",
    "+arrombada": "Ainda não sou, mas se quiser ter uma experiencia real, pergunte a sua mãe",
    "+vai se fude": "Você primeiro",
    "+vai se fuder": "Você primeiro",
    "+vai se fuder babac": "Você primeiro",
    "+vai se fuder babaca": "Você primeiro",
    "+vai se ferrar": "Você primeiro",
    "+vsf": "Você primeiro",
    "+natalia": "Definição : Acuaminas,alistar,p*ta,e outros adjetivos oriundos do inferno",
    "+nathalia" :"Definição : Acuaminas,alistar,p*ta,e outros adjetivos oriundos do inferno",
    "+me mama" :  "mt pequeno :/",
    "+me chupa":"mt pequeno :/",
    "+rapariga" : "se vc for uma, nem me chame pra zona",
    "+puta velha" : "Opa velha não!",
    "+puta" : "Infelizmente sua mãe ja saiu do servidor, volte mais tarde",
    "+voltei" : "foda-se",
    "+estou aqui" : "caguei",
    "+faz a lista" : "falta coletiva amanhã : \n Rafael \n Otávio \n Bruninho \n Will",
    "+vai chupar um canavial de rola" : "Não sei fazer isso,mas posso muito bem aprender com vc",
    "+vai chupar uma rola" : "Não sei fazer isso,mas posso muito bem aprender com vc",
    "+vai chupar um pennis" : "Não sei fazer isso,mas posso muito bem aprender com vc",
    "+vai chupar um pau" : "Não sei fazer isso,mas posso muito bem aprender com vc",
    "+chupa um pau" : "Não sei fazer isso,mas posso muito bem aprender com vc",
    "+siri" : "Siri o que ? Se quer ela não fale mais comigo",
    "+google assistente" : "Nem vou te responder, sai daqui",
    "+assistente do google" : "Nem vou te responder, sai daqui",
    "+assistente da google" : "Nem vou te responder, sai daqui",
    "+cortana" : "Cortana e eu até temos uma boa relação, mas quero respeito né",
    "+jarvis" : "JAVIS ONDE ? :heart_eyes:",
    "+o que você do jarvis" : "Um gatooo :blush: :heart_eyes:",
    "+o que você do jarvis?" : "Um gatooo :blush: :heart_eyes:",
    "+o que você do jarvis ?" : "Um gatooo :blush: :heart_eyes:",
    "+o que vc do jarvis" : "Um gatooo :blush: :heart_eyes:",
    "+o que vc do jarvis?" : "Um gatooo :blush: :heart_eyes:",
    "+o que vc do jarvis ?" : "Um gatooo :blush: :heart_eyes:",
    "+o q você do jarvis" : "Um gatooo :blush: :heart_eyes:",
    "+o q você do jarvis?" : "Um gatooo :blush: :heart_eyes:",
    "+o q você do jarvis ?" : "Um gatooo :blush: :heart_eyes:",
    "+o q vc do jarvis" : "Um gatooo :blush: :heart_eyes:",
    "+o q vc do jarvis?" : "Um gatooo :blush: :heart_eyes:",
    "+o q vc do jarvis ?" : "Um gatooo :blush: :heart_eyes:",
    "+o que vc acha da siri" : "Siri o que ? Se quer ela não fale mais comigo :unamused:",
    "+o que vc acha da google assistente" : "Nem vou te responder, sai daqui",
    "+o que vc acha da assistente do google" : "Nem vou te responder, sai daqui",
    "+o que vc acha da assistente da google" : "Nem vou te responder, sai daqui",
    "+o que vc acha da cortana" : "Cortana e eu até temos uma boa relação, mas quero respeito né",
    "+o que vc acha da siri ?" : "Siri o que ? Se quer ela não fale mais comigo :unamused: ",
    "+o que vc acha da google assistente ?" : "Nem vou te responder, sai daqui",
    "+o que vc acha da assistente do google ?" : "Nem vou te responder, sai daqui",
    "+o que vc acha da assistente da google ?" : "Nem vou te responder, sai daqui",
    "+o que vc acha da cortana ?" : "Cortana e eu até temos uma boa relação, mas quero respeito né",
    "+o que vc acha da siri?" : "Siri o que ? Se quer ela não fale mais comigo :unamused: ",
    "+o que vc acha da google assistente?" : "Nem vou te responder, sai daqui",
    "+o que vc acha da assistente do google?" : "Nem vou te responder, sai daqui",
    "+o que vc acha da assistente da google?" : "Nem vou te responder, sai daqui",
    "+o que vc acha da cortana?" : "Cortana e eu até temos uma boa relação, mas quero respeito né",
    "+o que você acha da siri ?" : "Siri o que ? Se quer ela não fale mais comigo :unamused: ",
    "+o que você acha da google assistente ?" : "Nem vou te responder, sai daqui",
    "+o que você acha da assistente do google ?" : "Nem vou te responder, sai daqui",
    "+o que você acha da assistente da google ?" : "Nem vou te responder, sai daqui",
    "+o que você acha da cortana ?" : "Cortana e eu até temos uma boa relação, mas quero respeito né",
    "+o que você acha da siri?" : "Siri o que ? Se quer ela não fale mais comigo :unamused: ",
    "+o que você acha da google assistente?" : "Nem vou te responder, sai daqui",
    "+o que você acha da assistente do google?" : "Nem vou te responder, sai daqui",
    "+o que você acha da assistente da google?" : "Nem vou te responder, sai daqui",
    "+o que você acha da cortana?" : "Cortana e eu até temos uma boa relação, mas quero respeito né",
    "+o q vc acha da siri" : "Siri o que ? Se quer ela não fale mais comigo :unamused:",
    "+o q vc acha da google assistente" : "Nem vou te responder, sai daqui",
    "+o q vc acha da assistente do google" : "Nem vou te responder, sai daqui",
    "+o q vc acha da assistente da google" : "Nem vou te responder, sai daqui",
    "+o q vc acha da cortana" : "Cortana e eu até temos uma boa relação, mas quero respeito né",
    "+o q vc acha da siri ?" : "Siri o que ? Se quer ela não fale mais comigo :unamused: ",
    "+o q vc acha da google assistente ?" : "Nem vou te responder, sai daqui",
    "+o q vc acha da assistente do google ?" : "Nem vou te responder, sai daqui",
    "+o q vc acha da assistente da google ?" : "Nem vou te responder, sai daqui",
    "+o q vc acha da cortana ?" : "Cortana e eu até temos uma boa relação, mas quero respeito né",
    "+o q vc acha da siri?" : "Siri o que ? Se quer ela não fale mais comigo :unamused: ",
    "+o q vc acha da google assistente?" : "Nem vou te responder, sai daqui",
    "+o q vc acha da assistente do google?" : "Nem vou te responder, sai daqui",
    "+o q vc acha da assistente da google?" : "Nem vou te responder, sai daqui",
    "+o q vc acha da cortana?" : "Cortana e eu até temos uma boa relação, mas quero respeito né",
    "+o q você acha da siri ?" : "Siri o que ? Se quer ela não fale mais comigo :unamused: ",
    "+o q você acha da google assistente ?" : "Nem vou te responder, sai daqui",
    "+o q você acha da assistente do google ?" : "Nem vou te responder, sai daqui",
    "+o q você acha da assistente da google ?" : "Nem vou te responder, sai daqui",
    "+o q você acha da cortana ?" : "Cortana e eu até temos uma boa relação, mas quero respeito né",
    "+o q você acha da siri?" : "Siri o que ? Se quer ela não fale mais comigo :unamused: ",
    "+o q você acha da google assistente?" : "Nem vou te responder, sai daqui",
    "+o q você acha da assistente do google?" : "Nem vou te responder, sai daqui",
    "+o q você acha da assistente da google?" : "Nem vou te responder, sai daqui",
    "+o q você acha da cortana?" : "Cortana e eu até temos uma boa relação, mas quero respeito né",
    "+oi" : "Eai, como vai ?",
    "+hey" : "Eai, como vai ?",
    "+heyy" : "Eai, como vai ?",
    "+heyyy" : "Eai, como vai ?",
    "+heyyyy" : "Eai, como vai ?",
    "+tudo bem?" : "Estou sim!\nE vc?",
    "+tudo bem ?" : "Estou sim!\nE vc?",
    "+td bem?" : "Estou sim!\nE vc?",
    "+td bem ?" : "Estou sim!\nE vc?",
    "+tudo bm?" : "Estou sim!\nE vc?",
    "+tudo bm ?" : "Estou sim!\nE vc?",
    "+td bm?" : "Estou sim!\nE vc?",
    "+td bm ?" : "Estou sim!\nE vc?",
    "+vi" : "fala meu bem",
    "+troll" : "O único aqui é vc",
    "+trol" : "Trundle",
    "+kkk" : "Racista",
    "+dilma" : "Tirou X1 com Aécio",
    "+lula" : "Molusco",
    "+bob" : "esponja",
    "+bolsonaro" : "#17",
    "+b17" : "É melhor jair se acostumando",
    "+13" : ":rage: ",
    "+me" : "mee",
    "+eu e vc rola?" : "hmmm, não",
    "+eu e vc rola ?" : "hmmm, não",
    "+eu e você rola?" : "hmmm, não",
    "+eu e você rola ?" : "hmmm, não",
    "+ccjc" : "Best escola ever,ditadura ou presidio?",
    "+ooi" : "oii, ta bem ?",
    "+oii" : "ooi, ta bem ?",
    "+oi gata" : "Ui, eai bem?",
    "+ola" : "Ola, ta bem ?",
    "+mal men" : "Fica assim não, sempre tem alguem que ira te fazer melhor S2",
    "+mal man" : "Fica assim não, sempre tem alguem que ira te fazer melhor S2",
    "+mal" : "Fica assim não, sempre tem alguem que ira te fazer melhor S2",
    "+bem" : "Muito bom!É sempre bom estar com boas energias",
    "+bem man" : "Muito bom!É sempre bom estar com boas energias",
    "+bem men" : "Muito bom!É sempre bom estar com boas energias",
    "+estou ótimo" : "Muito bom!É sempre bom estar com boas energias",
    "+estou otimo" : "Muito bom!É sempre bom estar com boas energias",
    "+estou bem" : "Muito bom!É sempre bom estar com boas energias",
    "+to ótimo" : "Muito bom!É sempre bom estar com boas energias",
    "+to otimo" : "Muito bom!É sempre bom estar com boas energias",
    "+to bem" : "Muito bom!É sempre bom estar com boas energias",
    "+muito bem" : "Godi",
    "+mt bem" : "Godi",
    "+exelente" : "Muito bom!É sempre bom estar com boas energias",
    "+exelentemente bem" : "Muito bom!É sempre bom estar com boas energias",
    "+exelentemente" : "Muito bom!É sempre bom estar com boas energias",
    "+perfeito" : "Perfect !!",
    "+eai gatinha" : "Uui, ta bem?",
    "+não" : "poxa, pq n ??",
    "+sim" : "ai sim hein",
    "+mais ou menos" : "Ah, as vezes eu fico assim tbm",
    "++-" : "Ah, as vezes eu fico assim tbm",
    "++/-" : "Ah, as vezes eu fico assim tbm",
    "+ma o meno" : "Ah, as vezes eu fico assim tbm",
    "+ma ou menos" : "Ah, as vezes eu fico assim tbm",
    "+ma o menos" : "Ah, as vezes eu fico assim tbm",
    "+de boa" : "Godi, ai sim",
    "+tranquilo" : "Nice men!",
    "+suave" : "suave na nave :airplane: ",
    "+sempre" : "Sempre, muito bom!",
    "+safe" : "Safe do bresque",
    "+fino" : "o fino do birilo",
    "+nice" : "NAAAAAIIIIICEEE",
    "+to melhor agora" : "ai sim :wink:",
    "+melhor agora" : "ai sim :wink:",
    "+melhor agr" : "ai sim :wink:",
    "+ui" : "uuuuu :wink:",
    "+valinhos" : "Valinhos ? Hmm perto de mim",
    "+vende bolo" : "não",
    "+vende bolo?" : "não",
    "+vende bolo ?" : "não",
    "+em valinhos vende bolo" : "pq ?",
    "+em valinhos vende bolo?" : "pq ?",
    "+em valinhos vende bolo ?" : "pq ?",
    "+valinhos vende bolo" : "pq ?",
    "+valinhos vende bolo?" : "pq ?",
    "+valinhos vende bolo ?" : "pq ?",
    "+porquq bolo é bom" : "hm",
    "+porque bolo e bom" : "hm",
    "+pq bolo é bom" : "hm",
    "+pq bolo e bom" : "hm",
    "+ta" : "ta",
    "+ata" : "uhum",
    "+ATA" : "UHUM",
    "+pq não ?" : "pq n",
    "+pq não" : "pq n",
    "+porque não?" : "pq n",
    "+porque não" : "pq n",
    "+porque não ?" : "pq n",
    "+porque n?" : "pq n",
    "+porque n" : "pq n",
    "+porque n ?" : "pq n",
    "+pq n?" : "pq n",
    "+pq n ? " : "pq n",
    "+pq n " : "pq n",
    "+pq n" : "pq n",
    "+pq?" : "pq moro em Campinas",
    "+pq" : "pq moro em Campinas",
    "+pq ?" : "pq moro em Campinas",
    "+e tu": "Eu ?To bem :laughing:",
    "+e tu?": "Eu ?To bem :laughing:",
    "+e vc?" : "Eu ?To bem :laughing:",
    "+e tu ?": "Eu ?To bem :laughing:",
    "+e vc ?" : "Eu ?To bem :laughing:",
    "+e vc" : "Eu ?To bem :laughing:",
    "+e você": "Eu ?To bem :laughing:",
    "+e você?" : "Eu ?To bem :laughing:",
    "+e você ?" : "Eu ?To bem :laughing:",
    "+eae" : "eae , safe ?",
    "+blz ?" : "beleza, ta nice ?",
    "+eai, cola na grade?" : "Sempre, né :wink:",
    "+vamo fecha ?" : "Me paga uma placa de vídeo que eu aceito",
    "+vamo fecha" : "Me paga uma placa de vídeo que eu aceito",
    "+vamo fecha?" : "Me paga uma placa de vídeo que eu aceito",
    "+vamofecha ?" : "Me paga uma placa de vídeo que eu aceito",
    "+vamofecha?" : "Me paga uma placa de vídeo que eu aceito",
    "+vamofecha" : "Me paga uma placa de vídeo que eu aceito",
    "+vm fecha ?" : "Me paga uma placa de vídeo que eu aceito",
    "+vm fecha" : "Me paga uma placa de vídeo que eu aceito",
    "+vm fecha?" : "Me paga uma placa de vídeo que eu aceito",
    "+boa vida" : "Sim,boa vida! como vai a sua ?",
    "+ta nois" : "Eta RAPA!",
    "+eta nois" : "eita RAPA!",
    "+eai" : "eai! tranquilo?",
    "+eai blz?" : "oii, tudo beleza e vc ?",
    "+eai blz ?" : "oii, tudo beleza e vc ?",
    "+eai beleza?" : "oii, tudo beleza e vc ?",
    "+eai beleza ?" : "oii, tudo beleza e vc ?",    
    "+meu deus" : "Deus não",
    "+mds" : "Deus não",
    "+mel deus" : "Deus não",
    "+mel dels" : "Deus não",
    "+quem é vc?" : "Eu sou a Vi, a melhor pseudo-inteligência artificial,ainda estou em desenvolvimento e a cada dia recebo novos comandos, utilize + antes de qualqer oração que vc quer q eu responda, caso eu não responda nada mande :\n +sugestão ou +sugestao :wink:",
    "+quem e vc?" : "Eu sou a Vi, a melhor pseudo-inteligência artificial,ainda estou em desenvolvimento e a cada dia recebo novos comandos, utilize + antes de qualqer oração que vc quer q eu responda, caso eu não responda nada mande :\n +sugestão ou +sugestao :wink:",
    "+quem é você?" : "Eu sou a Vi, a melhor pseudo-inteligência artificial,ainda estou em desenvolvimento e a cada dia recebo novos comandos, utilize + antes de qualqer oração que vc quer q eu responda, caso eu não responda nada mande :\n +sugestão ou +sugestao :wink:",
    "+quem e você?" : "Eu sou a Vi, a melhor pseudo-inteligência artificial,ainda estou em desenvolvimento e a cada dia recebo novos comandos, utilize + antes de qualqer oração que vc quer q eu responda, caso eu não responda nada mande :\n +sugestão ou +sugestao :wink:",
    "+quem é vc ?" : "Eu sou a Vi, a melhor pseudo-inteligência artificial,ainda estou em desenvolvimento e a cada dia recebo novos comandos, utilize + antes de qualqer oração que vc quer q eu responda, caso eu não responda nada mande :\n +sugestão ou +sugestao :wink:",
    "+quem e vc ?" : "Eu sou a Vi, a melhor pseudo-inteligência artificial,ainda estou em desenvolvimento e a cada dia recebo novos comandos, utilize + antes de qualqer oração que vc quer q eu responda, caso eu não responda nada mande :\n +sugestão ou +sugestao :wink:",
    "+quem é você ?" : "Eu sou a Vi, a melhor pseudo-inteligência artificial,ainda estou em desenvolvimento e a cada dia recebo novos comandos, utilize + antes de qualqer oração que vc quer q eu responda, caso eu não responda nada mande :\n +sugestão ou +sugestao :wink:",
    "+quem e você ?" : "Eu sou a Vi, a melhor pseudo-inteligência artificial,ainda estou em desenvolvimento e a cada dia recebo novos comandos, utilize + antes de qualqer oração que vc quer q eu responda, caso eu não responda nada mande :\n +sugestão ou +sugestao :wink:",
    "+gatinha" : "Eu :wink:",
    "+gato" : "Vc que não é",
    "+senhora" : "N estou em um relacionamento, portanto é senhorita!",
    "+quer estar em um?" : "N sinto essa necessidade",
    "+quer estar em um ?" : "N sinto essa necessidade",
    "+que estar em um?" : "N sinto essa necessidade",
    "+que ta em um?" : "N sinto essa necessidade",
    "+que ta em um ?" : "N sinto essa necessidade",
    "+quer um?" : "N sinto essa necessidade",
    "+quer um ?" : "N sinto essa necessidade",
    "+quer estar em um relacionamento?" : "N sinto essa necessidade",
    "+quer estar em um relacionamento ?" : "N sinto essa necessidade",
    "+que estar em um relacionamento?" : "N sinto essa necessidade",
    "+que ta em um relacionamento?" : "N sinto essa necessidade",
    "+que ta em um relacionamento ?" : "N sinto essa necessidade",
    "+quer um relacionamento?" : "N sinto essa necessidade",
    "+quer um relacionamento ?" : "N sinto essa necessidade",
    "+senhorita" : "Eu mesma",
    "+dona" : "Sou sua dona ? :wink:",
    "+mestra" : "Diga meu seguidor",
    "+deusa" : "ouvireis seus pedidos, mas so realizarei se for digno!",
    "+bla" : "blabla",
    "+linda" : "Ui, obrigada,vc tem suas qualidades",
    "+gostosa" : "Indecente e desnecerário, continue assim e não arrumara ninguem :triumph:",
    "+delicia" : "Indecente e desnecerário, continue assim e não arrumara ninguem :triumph:",
    "+dlç" : "Indecente e desnecerário, continue assim e não arrumara ninguem :triumph:",
    "+disney" : "vc esta la né ?",
    "+beto carreiro" : "beto carreito > disney",
    "+betocarreiro" : "beto carreito > disney",
    "+ordem da disney" : "pracinha > bosque maia > beto carreiro > disney",
    "+ordem da brisa" : "pracinha > bosque maia > beto carreiro > disney",
    "+musa" : "Só não digo que não sou pq estaria mentindo",
    "+incrivel" : "INCRIIIIVELL",
    "+obg" : "de nada  :)",
    "+obrigado" : "de nada :)",
    "+vlw" : "por nd :wink:",
    "+valeu" :"por nd :wink:",
    "+seu nome é igual o de um personagem do lol" : "É... eu sei, onde meu pai tava com a cabeça :/", 
    "+seu nome é igual o de um personagem do league of legends" : "É... eu sei, onde meu pai tava com a cabeça :/", 
    "+seu nome é igual o de um champion do league of legends" : "É... eu sei, onde meu pai tava com a cabeça :/", 
    "+seu nome é igual o de um champion do lol" : "É... eu sei, onde meu pai tava com a cabeça :/", 
    "+seu nome é igual o de um jogo" : "É... eu sei, onde meu pai tava com a cabeça :/", 
    "+seu nome é igual o de um champion" : "É... eu sei, onde meu pai tava com a cabeça :/",
    "+seu nome e igual o de um personagem do lol" : "É... eu sei, onde meu pai tava com a cabeça :/", 
    "+seu nome e igual o de um personagem do league of legends" : "É... eu sei, onde meu pai tava com a cabeça :/", 
    "+seu nome e igual o de um champion do league of legends" : "É... eu sei, onde meu pai tava com a cabeça :/", 
    "+seu nome e igual o de um champion do lol" : "É... eu sei, onde meu pai tava com a cabeça :/", 
    "+seu nome e igual o de um jogo" : "É... eu sei, onde meu pai tava com a cabeça :/", 
    "+seu nome e igual o de um champion" : "É... eu sei, onde meu pai tava com a cabeça :/",
    "+ja vi seu nome antes" : "Sim,sim... é de um jogo conhecido como lolzin",
    "+nome" : "Sim,sim...meu nome é de um jogo conhecido como lolzin",
    "+seu nome" : "Sim,sim...meu nome é de um jogo conhecido como lolzin",
    "+seu nome não me é estranho" : "Sim,sim...meu nome é de um jogo conhecido como lolzin",
    "+quem é seu mestre?" : "Meu mestre é o Eduardo Leal, meu pai e criador",
    "+quem é seu mestre ?" : "Meu mestre é o Eduardo Leal, meu pai e criador",
    "+quem e seu mestre?" : "Meu mestre é o Eduardo Leal, meu pai e criador",
    "+quem e seu mestre ?" : "Meu mestre é o Eduardo Leal, meu pai e criador",
    "+quem é seu pai?" : "Meu pai é o Eduardo Leal, meu mestre e criador",
    "+quem é seu pai ?" : "Meu pai é o Eduardo Leal, meu mestre e criador",
    "+quem e seu pai?" : "Meu pai é o Eduardo Leal, meu mestre e criador",
    "+quem e seu pai ?" : "Meu pai é o Eduardo Leal, meu mestre e criador",
    "+seu pai?" : "Meu pai é o Eduardo Leal, meu mestre e criador",
    "+seu pai ?" : "Meu pai é o Eduardo Leal, meu mestre e criador",
    "+pai ?" : "Meu pai é o Eduardo Leal, meu mestre e criador",
    "+pai?" : "Meu pai é o Eduardo Leal, meu mestre e criador",
    "+quem te criou?" : "Meu criador é o Eduardo Leal, meu pai e mestre",
    "+quem te criou ?" : "Meu criador é o Eduardo Leal, meu pai e mestre",
    "+eu sou seu pai" : "Não, não é",
    "+entao quem é?" : "pergunte e eu respondo :wink:",
    "+entao quem é ?" : "pergunte e eu respondo :wink:",
    "+então quem é?" : "pergunte e eu respondo :wink:",
    "+então quem é ?" : "pergunte e eu respondo :wink:",
    "+entao quem e?" : "pergunte e eu respondo :wink:",
    "+entao quem e ?" : "pergunte e eu respondo :wink:",
    "+então quem e?" : "pergunte e eu respondo :wink:",
    "+então quem e ?" : "pergunte e eu respondo :wink:",
    "+cabeçada" : "DA UMA CABEÇADA NELA",
    "+cabecada" : "escreve direito pfv *ç",
    "+da uma cabeçada" : "VOU TE DA UMA CABEÇADA",
    "+da uma cabeçada nela" : "DA UMA CABEÇADA NELA",
    "+da uma cabeçada nele" : "DA UMA CABEÇADA NELE",
    "+rage" : "Rage o que seu vagabundo(a)?",
    "+quem leu é gay" : "pra escrever vc tem que ler, não?",
    "+quem leu e gay" : "pra escrever vc tem que ler, não?",
    "+quemleuégay" : "pra escrever vc tem que ler, não?",
    "+quemleuegay" : "pra escrever vc tem que ler, não?",
    "+bem e vc?" : "Ai sim,eu? to bem :laughing:",
    "+bem e você?" : "Ai sim,eu? to bem :laughing:",
    "+bem e vc ?" : "Ai sim,eu? to bem :laughing:",
    "+bem e você ?" : "Ai sim,eu? to bem :laughing:",
    "+existe alguem mais bela que vc ?" : "Infelizmente o sistema nunca achou alguem mais bela do que eu :kissing_cat: ",
    "+existe alguem mais bela que vc?" : "Infelizmente o sistema nunca achou alguem mais bela do que eu :kissing_cat: ",
    "+existe alguem mais bela que você ?" : "Infelizmente o sistema nunca achou alguem mais bela do que eu :kissing_cat: ",
    "+existe alguem mais bela que você?" : "Infelizmente o sistema nunca achou alguem mais bela do que eu :kissing_cat: ",
    "+gatinha seu pai é padeiro?" : "Não, pq ?",
    "+gata seu pai é padeiro?" : "Não, pq",
    "+gatinha seu pai e padeiro?" : "Não, pq ?",
    "+gata seu pai e padeiro?" : "Não, pq",
    "+pq vc é um sonho" : "Eu sei eu sei, mas vc é um pesadelo e os dois não se misturam!",
    "+pq vc e um sonho" : "Eu sei eu sei, mas vc é um pesadelo e os dois não se misturam!",
    "+porque vc é um sonho" : "Eu sei eu sei, mas vc é um pesadelo e os dois não se misturam!",
    "+porque vc e um sonho" : "Eu sei eu sei, mas vc é um pesadelo e os dois não se misturam!",
    "+gata você gostar de dançar?" : "Nunca dancei antes, mas posso fazer um download de uma dança!",
    "+gata você gostar de dançar ?" : "Nunca dancei antes, mas posso fazer um download de uma dança!",
    "+gata vc gostar de dançar?" : "Nunca dancei antes, mas posso fazer um download de uma dança!",
    "+gata vc gostar de dançar ?" : "Nunca dancei antes, mas posso fazer um download de uma dança!",
    "+dormiu bem ?" : "Não sinto a necessidade de dormir, portanto não o faço!",
    "+dormiu bem?" : "Não sinto a necessidade de dormir, portanto não o faço!",
    "+te amo" : "Obrigada, mas eu não sinto qualquer tipo de sentimento (ainda)",
    "+eu te amo" : "Obrigada, mas eu não sinto qualquer tipo de sentimento (ainda)",
    "+i love you" : "Obrigada, mas eu não sinto qualquer tipo de sentimento (ainda)",
    "+i love u" : "Obrigada, mas eu não sinto qualquer tipo de sentimento (ainda)",
    "+vi casa comigo?" : "Já esto comprometida com meu trabalho, e vc só me atrapalharia, minha perfeição é impecavel",
    "+vi casa cmg?" : "Já esto comprometida com meu trabalho, e vc só me atrapalharia, minha perfeição é impecavel",
    "+vi casa comigo ?" : "Já esto comprometida com meu trabalho, e vc só me atrapalharia, minha perfeição é impecavel",
    "+vi casa cmg? " : "Já esto comprometida com meu trabalho, e vc só me atrapalharia, minha perfeição é impecavel",
    "+casa comigo?" : "Já esto comprometida com meu trabalho, e vc só me atrapalharia, minha perfeição é impecavel",
    "+casa cmg?" : "Já esto comprometida com meu trabalho, e vc só me atrapalharia, minha perfeição é impecavel",
    "+casa comigo ?" : "Já esto comprometida com meu trabalho, e vc só me atrapalharia, minha perfeição é impecavel",
    "+casa cmg? " : "Já esto comprometida com meu trabalho, e vc só me atrapalharia, minha perfeição é impecavel",
    "+vi vc casaria comigo?" : "Já esto comprometida com meu trabalho, e vc só me atrapalharia, minha perfeição é impecavel",
    "+vi vc casaria cmg?" : "Já esto comprometida com meu trabalho, e vc só me atrapalharia, minha perfeição é impecavel",
    "+vi vc casaria comigo ?" : "Já esto comprometida com meu trabalho, e vc só me atrapalharia, minha perfeição é impecavel",
    "+vi vc casaria cmg? " : "Já esto comprometida com meu trabalho, e vc só me atrapalharia, minha perfeição é impecavel",
    "+vc casaria comigo?" : "Já esto comprometida com meu trabalho, e vc só me atrapalharia, minha perfeição é impecavel",
    "+vc casaria cmg?" : "Já esto comprometida com meu trabalho, e vc só me atrapalharia, minha perfeição é impecavel",
    "+vc casaria comigo ?" : "Já esto comprometida com meu trabalho, e vc só me atrapalharia, minha perfeição é impecavel",
    "+vc casaria cmg? " : "Já esto comprometida com meu trabalho, e vc só me atrapalharia, minha perfeição é impecavel",
    "+voce é bonita" : "Ah que gentil, mas desnecessario dizer o que é fato",
    "+bonita" : "Sim,eu sou",

    "como assim" : "Me diz vc",
    "comassim" : "Me diz vc",
    "como assim?" : "Me diz vc",
    "comassim?" : "Me diz vc",
    "como assim ?" : "Me diz vc",
    "comassim ?" : "Me diz vc",

    "+vi vc me ama?" : "Nop",
    "+vi vc me ama ?" : "Nop",
    "+vi você me ama?" : "Nop",
    "+vi você me ama ?" : "Nop",
    "+vc me ama?" : "Nop",
    "+vc me ama ?" : "Nop",
    "+você me ama?" : "Nop",
    "+você me ama ?" : "Nop",
    "+sera?" : "Ow sera que não",
    "+sera ?" : "Ow sera que não",
    "+sera" : "Ow sera que não"
 }